{
  "name": "P755",
  "description": "ASCHHEIM",
  "days": {
    "Heute": [
      {
        "period": "Mittag",
        "icon": "https://raw.githubusercontent.com/stefan436/weather_image/main/docs/icons/low cloud cover.png",
        "label": "Bewölkung abnehmend",
        "avg": {
          "WW": 1.0,
          "TTT": -5.2,
          "RR1c": 0.0,
          "Neff": 49.0
        },
        "details": [
          {
            "timestamp": "2026-01-05T13:00:00+01:00",
            "WW": "1.00",
            "TTT": -5.3,
            "RR1c": "0.00",
            "Neff": "49.00"
          }
        ]
      },
      {
        "period": "Nachmittag",
        "icon": "https://raw.githubusercontent.com/stefan436/weather_image/main/docs/icons/low cloud cover.png",
        "label": "Bewölkung abnehmend",
        "avg": {
          "WW": 1.0,
          "TTT": -5.0,
          "RR1c": 0.0,
          "Neff": 41.8
        },
        "details": [
          {
            "timestamp": "2026-01-05T14:00:00+01:00",
            "WW": "1.00",
            "TTT": -4.8,
            "RR1c": "0.00",
            "Neff": "48.00"
          },
          {
            "timestamp": "2026-01-05T15:00:00+01:00",
            "WW": "1.00",
            "TTT": -4.8,
            "RR1c": "0.00",
            "Neff": "42.00"
          },
          {
            "timestamp": "2026-01-05T16:00:00+01:00",
            "WW": "1.00",
            "TTT": -5.0,
            "RR1c": "0.00",
            "Neff": "40.00"
          },
          {
            "timestamp": "2026-01-05T17:00:00+01:00",
            "WW": "1.00",
            "TTT": -5.5,
            "RR1c": "0.00",
            "Neff": "37.00"
          }
        ]
      },
      {
        "period": "Abend",
        "icon": "https://raw.githubusercontent.com/stefan436/weather_image/main/docs/icons/low cloud cover night.png",
        "label": "Bewölkung abnehmend",
        "avg": {
          "WW": 1.0,
          "TTT": -7.3,
          "RR1c": 0.0,
          "Neff": 38.5
        },
        "details": [
          {
            "timestamp": "2026-01-05T18:00:00+01:00",
            "WW": "1.00",
            "TTT": -6.3,
            "RR1c": "0.00",
            "Neff": "38.00"
          },
          {
            "timestamp": "2026-01-05T19:00:00+01:00",
            "WW": "1.00",
            "TTT": -7.1,
            "RR1c": "0.00",
            "Neff": "39.00"
          },
          {
            "timestamp": "2026-01-05T20:00:00+01:00",
            "WW": "1.00",
            "TTT": -7.7,
            "RR1c": "0.00",
            "Neff": "38.00"
          },
          {
            "timestamp": "2026-01-05T21:00:00+01:00",
            "WW": "1.00",
            "TTT": -8.3,
            "RR1c": "0.00",
            "Neff": "39.00"
          }
        ]
      },
      {
        "period": "Spät Abends",
        "icon": "https://raw.githubusercontent.com/stefan436/weather_image/main/docs/icons/low cloud cover night.png",
        "label": "Bewölkung abnehmend",
        "avg": {
          "WW": 1.0,
          "TTT": -9.4,
          "RR1c": 0.0,
          "Neff": 40.0
        },
        "details": [
          {
            "timestamp": "2026-01-05T22:00:00+01:00",
            "WW": "1.00",
            "TTT": -8.9,
            "RR1c": "0.00",
            "Neff": "37.00"
          },
          {
            "timestamp": "2026-01-05T23:00:00+01:00",
            "WW": "1.00",
            "TTT": -9.3,
            "RR1c": "0.00",
            "Neff": "39.00"
          },
          {
            "timestamp": "2026-01-06T00:00:00+01:00",
            "WW": "1.00",
            "TTT": -9.5,
            "RR1c": "0.00",
            "Neff": "41.00"
          },
          {
            "timestamp": "2026-01-06T01:00:00+01:00",
            "WW": "1.00",
            "TTT": -10.0,
            "RR1c": "0.00",
            "Neff": "43.00"
          }
        ]
      }
    ],
    "Morgen": [
      {
        "period": "Nacht",
        "icon": "https://raw.githubusercontent.com/stefan436/weather_image/main/docs/icons/medium cloud cover night.png",
        "label": "Bewölkung unverändert",
        "avg": {
          "WW": 1.0,
          "TTT": -10.2,
          "RR1c": 0.0,
          "Neff": 51.2
        },
        "details": [
          {
            "timestamp": "2026-01-06T02:00:00+01:00",
            "WW": "1.00",
            "TTT": -10.1,
            "RR1c": "0.00",
            "Neff": "46.00"
          },
          {
            "timestamp": "2026-01-06T03:00:00+01:00",
            "WW": "1.00",
            "TTT": -10.2,
            "RR1c": "0.00",
            "Neff": "47.00"
          },
          {
            "timestamp": "2026-01-06T04:00:00+01:00",
            "WW": "1.00",
            "TTT": -10.2,
            "RR1c": "0.00",
            "Neff": "54.00"
          },
          {
            "timestamp": "2026-01-06T05:00:00+01:00",
            "WW": "1.00",
            "TTT": -10.5,
            "RR1c": "0.00",
            "Neff": "58.00"
          }
        ]
      },
      {
        "period": "Früh",
        "icon": "https://raw.githubusercontent.com/stefan436/weather_image/main/docs/icons/medium cloud cover.png",
        "label": "Bewölkung unverändert",
        "avg": {
          "WW": 2.5,
          "TTT": -10.2,
          "RR1c": 0.0,
          "Neff": 66.5
        },
        "details": [
          {
            "timestamp": "2026-01-06T06:00:00+01:00",
            "WW": "2.00",
            "TTT": -10.6,
            "RR1c": "0.00",
            "Neff": "62.00"
          },
          {
            "timestamp": "2026-01-06T07:00:00+01:00",
            "WW": "2.00",
            "TTT": -10.5,
            "RR1c": "0.00",
            "Neff": "65.00"
          },
          {
            "timestamp": "2026-01-06T08:00:00+01:00",
            "WW": "3.00",
            "TTT": -10.2,
            "RR1c": "0.00",
            "Neff": "68.00"
          },
          {
            "timestamp": "2026-01-06T09:00:00+01:00",
            "WW": "3.00",
            "TTT": -9.6,
            "RR1c": "0.00",
            "Neff": "71.00"
          }
        ]
      },
      {
        "period": "Mittag",
        "icon": "https://raw.githubusercontent.com/stefan436/weather_image/main/docs/icons/medium cloud cover.png",
        "label": "Bewölkung unverändert",
        "avg": {
          "WW": 2.5,
          "TTT": -7.1,
          "RR1c": 0.0,
          "Neff": 70.5
        },
        "details": [
          {
            "timestamp": "2026-01-06T10:00:00+01:00",
            "WW": "3.00",
            "TTT": -8.6,
            "RR1c": "0.00",
            "Neff": "72.00"
          },
          {
            "timestamp": "2026-01-06T11:00:00+01:00",
            "WW": "3.00",
            "TTT": -7.6,
            "RR1c": "0.00",
            "Neff": "70.00"
          },
          {
            "timestamp": "2026-01-06T12:00:00+01:00",
            "WW": "2.00",
            "TTT": -6.6,
            "RR1c": "0.00",
            "Neff": "69.00"
          },
          {
            "timestamp": "2026-01-06T13:00:00+01:00",
            "WW": "2.00",
            "TTT": -5.7,
            "RR1c": "0.00",
            "Neff": "71.00"
          }
        ]
      },
      {
        "period": "Nachmittag",
        "icon": "https://raw.githubusercontent.com/stefan436/weather_image/main/docs/icons/medium cloud cover.png",
        "label": "Bewölkung unverändert",
        "avg": {
          "WW": 2.0,
          "TTT": -5.0,
          "RR1c": 0.0,
          "Neff": 73.5
        },
        "details": [
          {
            "timestamp": "2026-01-06T14:00:00+01:00",
            "WW": "2.00",
            "TTT": -5.1,
            "RR1c": "0.00",
            "Neff": "72.00"
          },
          {
            "timestamp": "2026-01-06T15:00:00+01:00",
            "WW": "2.00",
            "TTT": -5.0,
            "RR1c": "0.00",
            "Neff": "72.00"
          },
          {
            "timestamp": "2026-01-06T16:00:00+01:00",
            "WW": "2.00",
            "TTT": -5.0,
            "RR1c": "0.00",
            "Neff": "75.00"
          },
          {
            "timestamp": "2026-01-06T17:00:00+01:00",
            "WW": "2.00",
            "TTT": -5.0,
            "RR1c": "0.00",
            "Neff": "75.00"
          }
        ]
      },
      {
        "period": "Abend",
        "icon": "https://raw.githubusercontent.com/stefan436/weather_image/main/docs/icons/medium cloud cover night.png",
        "label": "Bewölkung unverändert",
        "avg": {
          "WW": 3.0,
          "TTT": -5.9,
          "RR1c": 0.0,
          "Neff": 76.8
        },
        "details": [
          {
            "timestamp": "2026-01-06T18:00:00+01:00",
            "WW": "3.00",
            "TTT": -5.4,
            "RR1c": "0.00",
            "Neff": "77.00"
          },
          {
            "timestamp": "2026-01-06T19:00:00+01:00",
            "WW": "3.00",
            "TTT": -5.8,
            "RR1c": "0.00",
            "Neff": "77.00"
          },
          {
            "timestamp": "2026-01-06T20:00:00+01:00",
            "WW": "3.00",
            "TTT": -6.0,
            "RR1c": "0.00",
            "Neff": "77.00"
          },
          {
            "timestamp": "2026-01-06T21:00:00+01:00",
            "WW": "3.00",
            "TTT": -6.5,
            "RR1c": "0.00",
            "Neff": "76.00"
          }
        ]
      },
      {
        "period": "Spät Abends",
        "icon": "https://raw.githubusercontent.com/stefan436/weather_image/main/docs/icons/medium cloud cover night.png",
        "label": "Bewölkung unverändert",
        "avg": {
          "WW": 3.0,
          "TTT": -7.3,
          "RR1c": 0.0,
          "Neff": 74.8
        },
        "details": [
          {
            "timestamp": "2026-01-06T22:00:00+01:00",
            "WW": "3.00",
            "TTT": -6.9,
            "RR1c": "0.00",
            "Neff": "75.00"
          },
          {
            "timestamp": "2026-01-06T23:00:00+01:00",
            "WW": "3.00",
            "TTT": -7.1,
            "RR1c": "0.00",
            "Neff": "76.00"
          },
          {
            "timestamp": "2026-01-07T00:00:00+01:00",
            "WW": "3.00",
            "TTT": -7.5,
            "RR1c": "0.00",
            "Neff": "75.00"
          },
          {
            "timestamp": "2026-01-07T01:00:00+01:00",
            "WW": "3.00",
            "TTT": -7.9,
            "RR1c": "0.00",
            "Neff": "73.00"
          }
        ]
      }
    ],
    "Übermorgen": [
      {
        "period": "Nacht",
        "icon": "https://raw.githubusercontent.com/stefan436/weather_image/main/docs/icons/medium cloud cover night.png",
        "label": "Bewölkung unverändert",
        "avg": {
          "WW": 2.5,
          "TTT": -8.5,
          "RR1c": 0.0,
          "Neff": 71.5
        },
        "details": [
          {
            "timestamp": "2026-01-07T02:00:00+01:00",
            "WW": "3.00",
            "TTT": -8.1,
            "RR1c": "0.00",
            "Neff": "73.00"
          },
          {
            "timestamp": "2026-01-07T03:00:00+01:00",
            "WW": "3.00",
            "TTT": -8.3,
            "RR1c": "0.00",
            "Neff": "72.00"
          },
          {
            "timestamp": "2026-01-07T04:00:00+01:00",
            "WW": "2.00",
            "TTT": -8.9,
            "RR1c": "0.00",
            "Neff": "71.00"
          },
          {
            "timestamp": "2026-01-07T05:00:00+01:00",
            "WW": "2.00",
            "TTT": -9.0,
            "RR1c": "0.00",
            "Neff": "70.00"
          }
        ]
      },
      {
        "period": "Früh",
        "icon": "https://raw.githubusercontent.com/stefan436/weather_image/main/docs/icons/medium cloud cover.png",
        "label": "Bewölkung unverändert",
        "avg": {
          "WW": 2.0,
          "TTT": -9.2,
          "RR1c": 0.0,
          "Neff": 70.5
        },
        "details": [
          {
            "timestamp": "2026-01-07T06:00:00+01:00",
            "WW": "2.00",
            "TTT": -9.0,
            "RR1c": "0.00",
            "Neff": "71.00"
          },
          {
            "timestamp": "2026-01-07T07:00:00+01:00",
            "WW": "2.00",
            "TTT": -9.5,
            "RR1c": "0.00",
            "Neff": "69.00"
          },
          {
            "timestamp": "2026-01-07T08:00:00+01:00",
            "WW": "2.00",
            "TTT": -9.4,
            "RR1c": "0.00",
            "Neff": "71.00"
          },
          {
            "timestamp": "2026-01-07T09:00:00+01:00",
            "WW": "2.00",
            "TTT": -9.1,
            "RR1c": "0.00",
            "Neff": "71.00"
          }
        ]
      },
      {
        "period": "Mittag",
        "icon": "https://raw.githubusercontent.com/stefan436/weather_image/main/docs/icons/medium cloud cover.png",
        "label": "Bewölkung unverändert",
        "avg": {
          "WW": 1.5,
          "TTT": -6.9,
          "RR1c": 0.0,
          "Neff": 54.8
        },
        "details": [
          {
            "timestamp": "2026-01-07T10:00:00+01:00",
            "WW": "2.00",
            "TTT": -8.3,
            "RR1c": "0.00",
            "Neff": "64.00"
          },
          {
            "timestamp": "2026-01-07T11:00:00+01:00",
            "WW": "2.00",
            "TTT": -7.5,
            "RR1c": "0.00",
            "Neff": "59.00"
          },
          {
            "timestamp": "2026-01-07T12:00:00+01:00",
            "WW": "1.00",
            "TTT": -6.4,
            "RR1c": "0.00",
            "Neff": "53.00"
          },
          {
            "timestamp": "2026-01-07T13:00:00+01:00",
            "WW": "1.00",
            "TTT": -5.5,
            "RR1c": "0.00",
            "Neff": "43.00"
          }
        ]
      },
      {
        "period": "Nachmittag",
        "icon": "https://raw.githubusercontent.com/stefan436/weather_image/main/docs/icons/low cloud cover.png",
        "label": "Bewölkung abnehmend",
        "avg": {
          "WW": 1.0,
          "TTT": -4.8,
          "RR1c": 0.0,
          "Neff": 41.2
        },
        "details": [
          {
            "timestamp": "2026-01-07T14:00:00+01:00",
            "WW": "1.00",
            "TTT": -4.8,
            "RR1c": "0.00",
            "Neff": "41.00"
          },
          {
            "timestamp": "2026-01-07T15:00:00+01:00",
            "WW": "1.00",
            "TTT": -4.5,
            "RR1c": "0.00",
            "Neff": "38.00"
          },
          {
            "timestamp": "2026-01-07T16:00:00+01:00",
            "WW": "1.00",
            "TTT": -4.7,
            "RR1c": "0.00",
            "Neff": "43.00"
          },
          {
            "timestamp": "2026-01-07T17:00:00+01:00",
            "WW": "1.00",
            "TTT": -5.3,
            "RR1c": "0.00",
            "Neff": "43.00"
          }
        ]
      },
      {
        "period": "Abend",
        "icon": "https://raw.githubusercontent.com/stefan436/weather_image/main/docs/icons/medium cloud cover night.png",
        "label": "Bewölkung unverändert",
        "avg": {
          "WW": 1.5,
          "TTT": -6.4,
          "RR1c": 0.0,
          "Neff": 56.0
        },
        "details": [
          {
            "timestamp": "2026-01-07T18:00:00+01:00",
            "WW": "1.00",
            "TTT": -6.0,
            "RR1c": "0.00",
            "Neff": "48.00"
          },
          {
            "timestamp": "2026-01-07T19:00:00+01:00",
            "WW": "1.00",
            "TTT": -6.4,
            "RR1c": "0.00",
            "Neff": "57.00"
          },
          {
            "timestamp": "2026-01-07T20:00:00+01:00",
            "WW": "2.00",
            "TTT": -6.7,
            "RR1c": "0.00",
            "Neff": "58.00"
          },
          {
            "timestamp": "2026-01-07T21:00:00+01:00",
            "WW": "2.00",
            "TTT": -6.7,
            "RR1c": "0.00",
            "Neff": "61.00"
          }
        ]
      },
      {
        "period": "Spät Abends",
        "icon": "https://raw.githubusercontent.com/stefan436/weather_image/main/docs/icons/medium cloud cover night.png",
        "label": "Bewölkung unverändert",
        "avg": {
          "WW": 2.5,
          "TTT": -5.8,
          "RR1c": 0.0,
          "Neff": 69.0
        },
        "details": [
          {
            "timestamp": "2026-01-07T22:00:00+01:00",
            "WW": "2.00",
            "TTT": -6.3,
            "RR1c": "0.00",
            "Neff": "65.00"
          },
          {
            "timestamp": "2026-01-07T23:00:00+01:00",
            "WW": "2.00",
            "TTT": -6.0,
            "RR1c": "0.00",
            "Neff": "66.00"
          },
          {
            "timestamp": "2026-01-08T00:00:00+01:00",
            "WW": "3.00",
            "TTT": -5.8,
            "RR1c": "0.00",
            "Neff": "70.00"
          },
          {
            "timestamp": "2026-01-08T01:00:00+01:00",
            "WW": "3.00",
            "TTT": -5.2,
            "RR1c": "0.00",
            "Neff": "75.00"
          }
        ]
      }
    ],
    "Thu, 08.01.": [
      {
        "period": "Nacht",
        "icon": "https://raw.githubusercontent.com/stefan436/weather_image/main/docs/icons/medium cloud cover night.png",
        "label": "Bewölkung unverändert",
        "avg": {
          "WW": 3.0,
          "TTT": -4.3,
          "RR1c": 0.0,
          "Neff": 77.5
        },
        "details": [
          {
            "timestamp": "2026-01-08T02:00:00+01:00",
            "WW": "3.00",
            "TTT": -4.9,
            "RR1c": "0.00",
            "Neff": "77.00"
          },
          {
            "timestamp": "2026-01-08T03:00:00+01:00",
            "WW": "3.00",
            "TTT": -4.5,
            "RR1c": "0.00",
            "Neff": "78.00"
          },
          {
            "timestamp": "2026-01-08T04:00:00+01:00",
            "WW": "3.00",
            "TTT": -4.2,
            "RR1c": "0.00",
            "Neff": "77.00"
          },
          {
            "timestamp": "2026-01-08T05:00:00+01:00",
            "WW": "3.00",
            "TTT": -4.0,
            "RR1c": "0.00",
            "Neff": "78.00"
          }
        ]
      },
      {
        "period": "Früh",
        "icon": "https://raw.githubusercontent.com/stefan436/weather_image/main/docs/icons/medium cloud cover.png",
        "label": "Bewölkung unverändert",
        "avg": {
          "WW": 3.0,
          "TTT": -3.2,
          "RR1c": 0.0,
          "Neff": 76.8
        },
        "details": [
          {
            "timestamp": "2026-01-08T06:00:00+01:00",
            "WW": "3.00",
            "TTT": -3.7,
            "RR1c": "0.00",
            "Neff": "78.00"
          },
          {
            "timestamp": "2026-01-08T07:00:00+01:00",
            "WW": "3.00",
            "TTT": -3.5,
            "RR1c": "0.00",
            "Neff": "76.00"
          },
          {
            "timestamp": "2026-01-08T08:00:00+01:00",
            "WW": "3.00",
            "TTT": -3.2,
            "RR1c": "0.00",
            "Neff": "77.00"
          },
          {
            "timestamp": "2026-01-08T09:00:00+01:00",
            "WW": "3.00",
            "TTT": -2.8,
            "RR1c": "0.00",
            "Neff": "76.00"
          }
        ]
      },
      {
        "period": "Mittag",
        "icon": "https://raw.githubusercontent.com/stefan436/weather_image/main/docs/icons/total cloud cover.png",
        "label": "Bewölkung zunehmend",
        "avg": {
          "WW": 3.0,
          "TTT": -1.3,
          "RR1c": 0.0,
          "Neff": 82.2
        },
        "details": [
          {
            "timestamp": "2026-01-08T10:00:00+01:00",
            "WW": "3.00",
            "TTT": -2.2,
            "RR1c": "0.00",
            "Neff": "81.00"
          },
          {
            "timestamp": "2026-01-08T11:00:00+01:00",
            "WW": "3.00",
            "TTT": -1.7,
            "RR1c": "0.00",
            "Neff": "80.00"
          },
          {
            "timestamp": "2026-01-08T12:00:00+01:00",
            "WW": "3.00",
            "TTT": -1.1,
            "RR1c": "0.00",
            "Neff": "82.00"
          },
          {
            "timestamp": "2026-01-08T13:00:00+01:00",
            "WW": "3.00",
            "TTT": -0.5,
            "RR1c": "0.00",
            "Neff": "86.00"
          }
        ]
      },
      {
        "period": "Nachmittag",
        "icon": "https://raw.githubusercontent.com/stefan436/weather_image/main/docs/icons/light snow.png",
        "label": "Leichter Schneefall",
        "avg": {
          "WW": 37.0,
          "TTT": 0.2,
          "RR1c": 0.4,
          "Neff": 87.8
        },
        "details": [
          {
            "timestamp": "2026-01-08T14:00:00+01:00",
            "WW": "3.00",
            "TTT": 0.2,
            "RR1c": "0.00",
            "Neff": "87.00"
          },
          {
            "timestamp": "2026-01-08T15:00:00+01:00",
            "WW": "3.00",
            "TTT": 0.4,
            "RR1c": "0.00",
            "Neff": "87.00"
          },
          {
            "timestamp": "2026-01-08T16:00:00+01:00",
            "WW": "71.00",
            "TTT": 0.2,
            "RR1c": "0.30",
            "Neff": "88.00"
          },
          {
            "timestamp": "2026-01-08T17:00:00+01:00",
            "WW": "71.00",
            "TTT": 0.2,
            "RR1c": "0.10",
            "Neff": "89.00"
          }
        ]
      },
      {
        "period": "Abend",
        "icon": "https://raw.githubusercontent.com/stefan436/weather_image/main/docs/icons/light snow.png",
        "label": "Leichter Schneefall",
        "avg": {
          "WW": 71.0,
          "TTT": 0.5,
          "RR1c": 0.8,
          "Neff": 92.5
        },
        "details": [
          {
            "timestamp": "2026-01-08T18:00:00+01:00",
            "WW": "71.00",
            "TTT": 0.1,
            "RR1c": "0.10",
            "Neff": "90.00"
          },
          {
            "timestamp": "2026-01-08T19:00:00+01:00",
            "WW": "71.00",
            "TTT": 0.2,
            "RR1c": "0.20",
            "Neff": "93.00"
          },
          {
            "timestamp": "2026-01-08T20:00:00+01:00",
            "WW": "71.00",
            "TTT": 0.6,
            "RR1c": "0.20",
            "Neff": "93.00"
          },
          {
            "timestamp": "2026-01-08T21:00:00+01:00",
            "WW": "71.00",
            "TTT": 0.8,
            "RR1c": "0.30",
            "Neff": "94.00"
          }
        ]
      },
      {
        "period": "Spät Abends",
        "icon": "https://raw.githubusercontent.com/stefan436/weather_image/main/docs/icons/light sleet.png",
        "label": "Leichter Schneeregen",
        "avg": {
          "WW": 66.2,
          "TTT": 1.6,
          "RR1c": 1.6,
          "Neff": 96.0
        },
        "details": [
          {
            "timestamp": "2026-01-08T22:00:00+01:00",
            "WW": "68.00",
            "TTT": 1.2,
            "RR1c": "0.40",
            "Neff": "95.00"
          },
          {
            "timestamp": "2026-01-08T23:00:00+01:00",
            "WW": "68.00",
            "TTT": 1.5,
            "RR1c": "0.40",
            "Neff": "96.00"
          },
          {
            "timestamp": "2026-01-09T00:00:00+01:00",
            "WW": "68.00",
            "TTT": 1.7,
            "RR1c": "0.40",
            "Neff": "96.00"
          },
          {
            "timestamp": "2026-01-09T01:00:00+01:00",
            "WW": "61.00",
            "TTT": 1.9,
            "RR1c": "0.40",
            "Neff": "97.00"
          }
        ]
      }
    ],
    "Fri, 09.01.": [
      {
        "period": "Nacht",
        "icon": "https://raw.githubusercontent.com/stefan436/weather_image/main/docs/icons/light rain.png",
        "label": "Leichter Regen",
        "avg": {
          "WW": 61.0,
          "TTT": 2.6,
          "RR1c": 1.3,
          "Neff": 95.5
        },
        "details": [
          {
            "timestamp": "2026-01-09T02:00:00+01:00",
            "WW": "61.00",
            "TTT": 2.4,
            "RR1c": "0.40",
            "Neff": "97.00"
          },
          {
            "timestamp": "2026-01-09T03:00:00+01:00",
            "WW": "61.00",
            "TTT": 2.5,
            "RR1c": "0.30",
            "Neff": "95.00"
          },
          {
            "timestamp": "2026-01-09T04:00:00+01:00",
            "WW": "61.00",
            "TTT": 2.7,
            "RR1c": "0.30",
            "Neff": "95.00"
          },
          {
            "timestamp": "2026-01-09T05:00:00+01:00",
            "WW": "61.00",
            "TTT": 2.7,
            "RR1c": "0.30",
            "Neff": "95.00"
          }
        ]
      },
      {
        "period": "Früh",
        "icon": "https://raw.githubusercontent.com/stefan436/weather_image/main/docs/icons/light rain.png",
        "label": "Leichter Regen",
        "avg": {
          "WW": 61.0,
          "TTT": 3.2,
          "RR1c": 1.3,
          "Neff": 91.8
        },
        "details": [
          {
            "timestamp": "2026-01-09T06:00:00+01:00",
            "WW": "61.00",
            "TTT": 3.0,
            "RR1c": "0.30",
            "Neff": "95.00"
          },
          {
            "timestamp": "2026-01-09T07:00:00+01:00",
            "WW": "61.00",
            "TTT": 3.2,
            "RR1c": "0.30",
            "Neff": "92.00"
          },
          {
            "timestamp": "2026-01-09T08:00:00+01:00",
            "WW": "61.00",
            "TTT": 3.4,
            "RR1c": "0.30",
            "Neff": "91.00"
          },
          {
            "timestamp": "2026-01-09T09:00:00+01:00",
            "WW": "61.00",
            "TTT": 3.4,
            "RR1c": "0.40",
            "Neff": "89.00"
          }
        ]
      },
      {
        "period": "Mittag",
        "icon": "https://raw.githubusercontent.com/stefan436/weather_image/main/docs/icons/light rain.png",
        "label": "Leichter Regen",
        "avg": {
          "WW": 17.5,
          "TTT": 4.2,
          "RR1c": 0.4,
          "Neff": 86.0
        },
        "details": [
          {
            "timestamp": "2026-01-09T10:00:00+01:00",
            "WW": "61.00",
            "TTT": 3.6,
            "RR1c": "0.40",
            "Neff": "88.00"
          },
          {
            "timestamp": "2026-01-09T11:00:00+01:00",
            "WW": "3.00",
            "TTT": 4.2,
            "RR1c": "0.00",
            "Neff": "87.00"
          },
          {
            "timestamp": "2026-01-09T12:00:00+01:00",
            "WW": "3.00",
            "TTT": 4.5,
            "RR1c": "0.00",
            "Neff": "84.00"
          },
          {
            "timestamp": "2026-01-09T13:00:00+01:00",
            "WW": "3.00",
            "TTT": 4.3,
            "RR1c": "0.00",
            "Neff": "85.00"
          }
        ]
      },
      {
        "period": "Nachmittag",
        "icon": "https://raw.githubusercontent.com/stefan436/weather_image/main/docs/icons/total cloud cover.png",
        "label": "Bewölkung zunehmend",
        "avg": {
          "WW": 3.0,
          "TTT": 4.2,
          "RR1c": 0.0,
          "Neff": 85.5
        },
        "details": [
          {
            "timestamp": "2026-01-09T14:00:00+01:00",
            "WW": "3.00",
            "TTT": 4.6,
            "RR1c": "0.00",
            "Neff": "86.00"
          },
          {
            "timestamp": "2026-01-09T15:00:00+01:00",
            "WW": "3.00",
            "TTT": 4.5,
            "RR1c": "0.00",
            "Neff": "85.00"
          },
          {
            "timestamp": "2026-01-09T16:00:00+01:00",
            "WW": "3.00",
            "TTT": 4.1,
            "RR1c": "0.00",
            "Neff": "84.00"
          },
          {
            "timestamp": "2026-01-09T17:00:00+01:00",
            "WW": "3.00",
            "TTT": 3.7,
            "RR1c": "0.00",
            "Neff": "87.00"
          }
        ]
      },
      {
        "period": "Abend",
        "icon": "https://raw.githubusercontent.com/stefan436/weather_image/main/docs/icons/light sleet.png",
        "label": "Leichter Schneeregen",
        "avg": {
          "WW": 64.5,
          "TTT": 3.0,
          "RR1c": 0.0,
          "Neff": 91.5
        },
        "details": [
          {
            "timestamp": "2026-01-09T18:00:00+01:00",
            "WW": "61.00",
            "TTT": 3.4,
            "RR1c": "0.00",
            "Neff": "88.00"
          },
          {
            "timestamp": "2026-01-09T19:00:00+01:00",
            "WW": "68.00",
            "TTT": 3.1,
            "RR1c": "0.00",
            "Neff": "91.00"
          },
          {
            "timestamp": "2026-01-09T20:00:00+01:00",
            "WW": "68.00",
            "TTT": 2.8,
            "RR1c": "0.00",
            "Neff": "93.00"
          },
          {
            "timestamp": "2026-01-09T21:00:00+01:00",
            "WW": "61.00",
            "TTT": 2.7,
            "RR1c": "0.00",
            "Neff": "94.00"
          }
        ]
      },
      {
        "period": "Spät Abends",
        "icon": "https://raw.githubusercontent.com/stefan436/weather_image/main/docs/icons/light sleet.png",
        "label": "Leichter Schneeregen",
        "avg": {
          "WW": 68.0,
          "TTT": 2.6,
          "RR1c": 0.0,
          "Neff": 94.2
        },
        "details": [
          {
            "timestamp": "2026-01-09T22:00:00+01:00",
            "WW": "68.00",
            "TTT": 2.8,
            "RR1c": "0.00",
            "Neff": "93.00"
          },
          {
            "timestamp": "2026-01-09T23:00:00+01:00",
            "WW": "68.00",
            "TTT": 2.6,
            "RR1c": "0.00",
            "Neff": "94.00"
          },
          {
            "timestamp": "2026-01-10T00:00:00+01:00",
            "WW": "68.00",
            "TTT": 2.5,
            "RR1c": "0.00",
            "Neff": "95.00"
          },
          {
            "timestamp": "2026-01-10T01:00:00+01:00",
            "WW": "68.00",
            "TTT": 2.4,
            "RR1c": "0.00",
            "Neff": "95.00"
          }
        ]
      }
    ],
    "Sat, 10.01.": [
      {
        "period": "Nacht",
        "icon": "https://raw.githubusercontent.com/stefan436/weather_image/main/docs/icons/light snow.png",
        "label": "Leichter Schneefall",
        "avg": {
          "WW": 69.5,
          "TTT": 2.2,
          "RR1c": 0.8,
          "Neff": 96.2
        },
        "details": [
          {
            "timestamp": "2026-01-10T02:00:00+01:00",
            "WW": "68.00",
            "TTT": 2.4,
            "RR1c": "0.00",
            "Neff": "96.00"
          },
          {
            "timestamp": "2026-01-10T03:00:00+01:00",
            "WW": "68.00",
            "TTT": 2.3,
            "RR1c": "0.00",
            "Neff": "97.00"
          },
          {
            "timestamp": "2026-01-10T04:00:00+01:00",
            "WW": "71.00",
            "TTT": 2.1,
            "RR1c": "0.00",
            "Neff": "96.00"
          },
          {
            "timestamp": "2026-01-10T05:00:00+01:00",
            "WW": "71.00",
            "TTT": 2.1,
            "RR1c": "0.80",
            "Neff": "96.00"
          }
        ]
      },
      {
        "period": "Früh",
        "icon": "https://raw.githubusercontent.com/stefan436/weather_image/main/docs/icons/light snow.png",
        "label": "Leichter Schneefall",
        "avg": {
          "WW": 71.0,
          "TTT": 2.0,
          "RR1c": 1.8,
          "Neff": 94.0
        },
        "details": [
          {
            "timestamp": "2026-01-10T06:00:00+01:00",
            "WW": "71.00",
            "TTT": 2.0,
            "RR1c": "0.80",
            "Neff": "96.00"
          },
          {
            "timestamp": "2026-01-10T07:00:00+01:00",
            "WW": "71.00",
            "TTT": 1.9,
            "RR1c": "0.70",
            "Neff": "94.00"
          },
          {
            "timestamp": "2026-01-10T08:00:00+01:00",
            "WW": "71.00",
            "TTT": 2.0,
            "RR1c": "0.10",
            "Neff": "93.00"
          },
          {
            "timestamp": "2026-01-10T09:00:00+01:00",
            "WW": "71.00",
            "TTT": 1.8,
            "RR1c": "0.20",
            "Neff": "93.00"
          }
        ]
      },
      {
        "period": "Mittag",
        "icon": "https://raw.githubusercontent.com/stefan436/weather_image/main/docs/icons/light snow.png",
        "label": "Leichter Schneefall",
        "avg": {
          "WW": 71.0,
          "TTT": 2.1,
          "RR1c": 0.6,
          "Neff": 91.5
        },
        "details": [
          {
            "timestamp": "2026-01-10T10:00:00+01:00",
            "WW": "71.00",
            "TTT": 1.9,
            "RR1c": "0.10",
            "Neff": "92.00"
          },
          {
            "timestamp": "2026-01-10T11:00:00+01:00",
            "WW": "71.00",
            "TTT": 2.2,
            "RR1c": "0.20",
            "Neff": "92.00"
          },
          {
            "timestamp": "2026-01-10T12:00:00+01:00",
            "WW": "71.00",
            "TTT": 2.2,
            "RR1c": "0.20",
            "Neff": "91.00"
          },
          {
            "timestamp": "2026-01-10T13:00:00+01:00",
            "WW": "71.00",
            "TTT": 1.9,
            "RR1c": "0.10",
            "Neff": "91.00"
          }
        ]
      },
      {
        "period": "Nachmittag",
        "icon": "https://raw.githubusercontent.com/stefan436/weather_image/main/docs/icons/light snow.png",
        "label": "Leichter Schneefall",
        "avg": {
          "WW": 71.0,
          "TTT": 1.4,
          "RR1c": 0.4,
          "Neff": 91.0
        },
        "details": [
          {
            "timestamp": "2026-01-10T14:00:00+01:00",
            "WW": "71.00",
            "TTT": 1.9,
            "RR1c": "0.10",
            "Neff": "91.00"
          },
          {
            "timestamp": "2026-01-10T15:00:00+01:00",
            "WW": "71.00",
            "TTT": 1.7,
            "RR1c": "0.10",
            "Neff": "90.00"
          },
          {
            "timestamp": "2026-01-10T16:00:00+01:00",
            "WW": "71.00",
            "TTT": 1.1,
            "RR1c": "0.10",
            "Neff": "92.00"
          },
          {
            "timestamp": "2026-01-10T17:00:00+01:00",
            "WW": "71.00",
            "TTT": 0.8,
            "RR1c": "0.10",
            "Neff": "91.00"
          }
        ]
      },
      {
        "period": "Abend",
        "icon": "https://raw.githubusercontent.com/stefan436/weather_image/main/docs/icons/light snow.png",
        "label": "Leichter Schneefall",
        "avg": {
          "WW": 71.0,
          "TTT": -0.0,
          "RR1c": 0.5,
          "Neff": 91.8
        },
        "details": [
          {
            "timestamp": "2026-01-10T18:00:00+01:00",
            "WW": "71.00",
            "TTT": 0.3,
            "RR1c": "0.10",
            "Neff": "91.00"
          },
          {
            "timestamp": "2026-01-10T19:00:00+01:00",
            "WW": "71.00",
            "TTT": -0.1,
            "RR1c": "0.20",
            "Neff": "92.00"
          },
          {
            "timestamp": "2026-01-10T20:00:00+01:00",
            "WW": "71.00",
            "TTT": -0.1,
            "RR1c": "0.10",
            "Neff": "92.00"
          },
          {
            "timestamp": "2026-01-10T21:00:00+01:00",
            "WW": "71.00",
            "TTT": -0.2,
            "RR1c": "0.10",
            "Neff": "92.00"
          }
        ]
      },
      {
        "period": "Spät Abends",
        "icon": "https://raw.githubusercontent.com/stefan436/weather_image/main/docs/icons/light snow.png",
        "label": "Leichter Schneefall",
        "avg": {
          "WW": 71.0,
          "TTT": -0.5,
          "RR1c": 0.4,
          "Neff": 89.8
        },
        "details": [
          {
            "timestamp": "2026-01-10T22:00:00+01:00",
            "WW": "71.00",
            "TTT": -0.3,
            "RR1c": "0.10",
            "Neff": "91.00"
          },
          {
            "timestamp": "2026-01-10T23:00:00+01:00",
            "WW": "71.00",
            "TTT": -0.4,
            "RR1c": "0.10",
            "Neff": "90.00"
          },
          {
            "timestamp": "2026-01-11T00:00:00+01:00",
            "WW": "71.00",
            "TTT": -0.6,
            "RR1c": "0.10",
            "Neff": "89.00"
          },
          {
            "timestamp": "2026-01-11T01:00:00+01:00",
            "WW": "71.00",
            "TTT": -0.8,
            "RR1c": "0.10",
            "Neff": "89.00"
          }
        ]
      }
    ],
    "Sun, 11.01.": [
      {
        "period": "Nacht",
        "icon": "https://raw.githubusercontent.com/stefan436/weather_image/main/docs/icons/light snow.png",
        "label": "Leichter Schneefall",
        "avg": {
          "WW": 71.0,
          "TTT": -1.0,
          "RR1c": 0.4,
          "Neff": 85.8
        },
        "details": [
          {
            "timestamp": "2026-01-11T02:00:00+01:00",
            "WW": "71.00",
            "TTT": -0.9,
            "RR1c": "0.10",
            "Neff": "89.00"
          },
          {
            "timestamp": "2026-01-11T03:00:00+01:00",
            "WW": "71.00",
            "TTT": -1.0,
            "RR1c": "0.10",
            "Neff": "87.00"
          },
          {
            "timestamp": "2026-01-11T04:00:00+01:00",
            "WW": "71.00",
            "TTT": -1.1,
            "RR1c": "0.10",
            "Neff": "84.00"
          },
          {
            "timestamp": "2026-01-11T05:00:00+01:00",
            "WW": "71.00",
            "TTT": -1.2,
            "RR1c": "0.10",
            "Neff": "83.00"
          }
        ]
      },
      {
        "period": "Früh",
        "icon": "https://raw.githubusercontent.com/stefan436/weather_image/main/docs/icons/light snow.png",
        "label": "Leichter Schneefall",
        "avg": {
          "WW": 71.0,
          "TTT": -1.1,
          "RR1c": 0.9,
          "Neff": 81.8
        },
        "details": [
          {
            "timestamp": "2026-01-11T06:00:00+01:00",
            "WW": "71.00",
            "TTT": -1.3,
            "RR1c": "0.10",
            "Neff": "82.00"
          },
          {
            "timestamp": "2026-01-11T07:00:00+01:00",
            "WW": "71.00",
            "TTT": -1.3,
            "RR1c": "0.10",
            "Neff": "81.00"
          },
          {
            "timestamp": "2026-01-11T08:00:00+01:00",
            "WW": "71.00",
            "TTT": -1.4,
            "RR1c": "0.30",
            "Neff": "82.00"
          },
          {
            "timestamp": "2026-01-11T09:00:00+01:00",
            "WW": "71.00",
            "TTT": -0.8,
            "RR1c": "0.40",
            "Neff": "82.00"
          }
        ]
      },
      {
        "period": "Mittag",
        "icon": "https://raw.githubusercontent.com/stefan436/weather_image/main/docs/icons/total cloud cover.png",
        "label": "Bewölkung zunehmend",
        "avg": {
          "WW": 3.0,
          "TTT": 0.2,
          "RR1c": 0.0,
          "Neff": 82.0
        },
        "details": [
          {
            "timestamp": "2026-01-11T10:00:00+01:00",
            "WW": "3.00",
            "TTT": -0.4,
            "RR1c": "0.00",
            "Neff": "82.00"
          },
          {
            "timestamp": "2026-01-11T11:00:00+01:00",
            "WW": "3.00",
            "TTT": 0.1,
            "RR1c": "0.00",
            "Neff": "82.00"
          },
          {
            "timestamp": "2026-01-11T12:00:00+01:00",
            "WW": "3.00",
            "TTT": 0.6,
            "RR1c": "0.00",
            "Neff": "82.00"
          },
          {
            "timestamp": "2026-01-11T13:00:00+01:00",
            "WW": "3.00",
            "TTT": 0.9,
            "RR1c": "0.00",
            "Neff": "82.00"
          }
        ]
      },
      {
        "period": "Nachmittag",
        "icon": "https://raw.githubusercontent.com/stefan436/weather_image/main/docs/icons/total cloud cover.png",
        "label": "Bewölkung zunehmend",
        "avg": {
          "WW": 3.0,
          "TTT": 0.7,
          "RR1c": 0.0,
          "Neff": 84.0
        },
        "details": [
          {
            "timestamp": "2026-01-11T14:00:00+01:00",
            "WW": "3.00",
            "TTT": 0.8,
            "RR1c": "0.00",
            "Neff": "83.00"
          },
          {
            "timestamp": "2026-01-11T15:00:00+01:00",
            "WW": "3.00",
            "TTT": 0.9,
            "RR1c": "0.00",
            "Neff": "84.00"
          },
          {
            "timestamp": "2026-01-11T16:00:00+01:00",
            "WW": "3.00",
            "TTT": 0.6,
            "RR1c": "0.00",
            "Neff": "84.00"
          },
          {
            "timestamp": "2026-01-11T17:00:00+01:00",
            "WW": "3.00",
            "TTT": 0.2,
            "RR1c": "0.00",
            "Neff": "85.00"
          }
        ]
      },
      {
        "period": "Abend",
        "icon": "https://raw.githubusercontent.com/stefan436/weather_image/main/docs/icons/total cloud cover.png",
        "label": "Bewölkung zunehmend",
        "avg": {
          "WW": 3.0,
          "TTT": -0.4,
          "RR1c": 0.0,
          "Neff": 88.8
        },
        "details": [
          {
            "timestamp": "2026-01-11T18:00:00+01:00",
            "WW": "3.00",
            "TTT": -0.3,
            "RR1c": "0.00",
            "Neff": "87.00"
          },
          {
            "timestamp": "2026-01-11T19:00:00+01:00",
            "WW": "3.00",
            "TTT": -0.4,
            "RR1c": "0.00",
            "Neff": "90.00"
          },
          {
            "timestamp": "2026-01-11T20:00:00+01:00",
            "WW": "3.00",
            "TTT": -0.5,
            "RR1c": "0.00",
            "Neff": "89.00"
          },
          {
            "timestamp": "2026-01-11T21:00:00+01:00",
            "WW": "3.00",
            "TTT": -0.5,
            "RR1c": "0.00",
            "Neff": "89.00"
          }
        ]
      },
      {
        "period": "Spät Abends",
        "icon": "https://raw.githubusercontent.com/stefan436/weather_image/main/docs/icons/light sleet.png",
        "label": "Leichter Schneeregen",
        "avg": {
          "WW": 19.2,
          "TTT": -0.8,
          "RR1c": 0.0,
          "Neff": 89.5
        },
        "details": [
          {
            "timestamp": "2026-01-11T22:00:00+01:00",
            "WW": "68.00",
            "TTT": -0.7,
            "RR1c": "0.00",
            "Neff": "89.00"
          },
          {
            "timestamp": "2026-01-11T23:00:00+01:00",
            "WW": "3.00",
            "TTT": -0.7,
            "RR1c": "0.00",
            "Neff": "89.00"
          },
          {
            "timestamp": "2026-01-12T00:00:00+01:00",
            "WW": "3.00",
            "TTT": -0.7,
            "RR1c": "0.00",
            "Neff": "89.00"
          },
          {
            "timestamp": "2026-01-12T01:00:00+01:00",
            "WW": "3.00",
            "TTT": -0.9,
            "RR1c": "0.00",
            "Neff": "91.00"
          }
        ]
      }
    ],
    "Mon, 12.01.": [
      {
        "period": "Nacht",
        "icon": "https://raw.githubusercontent.com/stefan436/weather_image/main/docs/icons/total cloud cover.png",
        "label": "Bewölkung zunehmend",
        "avg": {
          "WW": 3.0,
          "TTT": -0.8,
          "RR1c": 0.0,
          "Neff": 89.8
        },
        "details": [
          {
            "timestamp": "2026-01-12T02:00:00+01:00",
            "WW": "3.00",
            "TTT": -0.9,
            "RR1c": "0.00",
            "Neff": "90.00"
          },
          {
            "timestamp": "2026-01-12T03:00:00+01:00",
            "WW": "3.00",
            "TTT": -0.8,
            "RR1c": "0.00",
            "Neff": "89.00"
          },
          {
            "timestamp": "2026-01-12T04:00:00+01:00",
            "WW": "3.00",
            "TTT": -0.7,
            "RR1c": "0.00",
            "Neff": "90.00"
          },
          {
            "timestamp": "2026-01-12T05:00:00+01:00",
            "WW": "3.00",
            "TTT": -0.7,
            "RR1c": "0.00",
            "Neff": "90.00"
          }
        ]
      },
      {
        "period": "Früh",
        "icon": "https://raw.githubusercontent.com/stefan436/weather_image/main/docs/icons/total cloud cover.png",
        "label": "Bewölkung zunehmend",
        "avg": {
          "WW": 3.0,
          "TTT": -0.1,
          "RR1c": 0.0,
          "Neff": 89.0
        },
        "details": [
          {
            "timestamp": "2026-01-12T06:00:00+01:00",
            "WW": "3.00",
            "TTT": -0.6,
            "RR1c": "0.00",
            "Neff": "89.00"
          },
          {
            "timestamp": "2026-01-12T07:00:00+01:00",
            "WW": "3.00",
            "TTT": -0.2,
            "RR1c": "0.00",
            "Neff": "89.00"
          },
          {
            "timestamp": "2026-01-12T08:00:00+01:00",
            "WW": "3.00",
            "TTT": 0.0,
            "RR1c": "0.00",
            "Neff": "89.00"
          },
          {
            "timestamp": "2026-01-12T09:00:00+01:00",
            "WW": "3.00",
            "TTT": 0.1,
            "RR1c": "0.00",
            "Neff": "89.00"
          }
        ]
      },
      {
        "period": "Mittag",
        "icon": "https://raw.githubusercontent.com/stefan436/weather_image/main/docs/icons/total cloud cover.png",
        "label": "Bewölkung zunehmend",
        "avg": {
          "WW": 3.0,
          "TTT": 1.2,
          "RR1c": 0.0,
          "Neff": 88.2
        },
        "details": [
          {
            "timestamp": "2026-01-12T10:00:00+01:00",
            "WW": "3.00",
            "TTT": 0.6,
            "RR1c": "0.00",
            "Neff": "88.00"
          },
          {
            "timestamp": "2026-01-12T11:00:00+01:00",
            "WW": "3.00",
            "TTT": 1.0,
            "RR1c": "0.00",
            "Neff": "89.00"
          },
          {
            "timestamp": "2026-01-12T12:00:00+01:00",
            "WW": "3.00",
            "TTT": 1.4,
            "RR1c": "0.00",
            "Neff": "88.00"
          },
          {
            "timestamp": "2026-01-12T13:00:00+01:00",
            "WW": "3.00",
            "TTT": 1.9,
            "RR1c": "0.00",
            "Neff": "88.00"
          }
        ]
      },
      {
        "period": "Nachmittag",
        "icon": "https://raw.githubusercontent.com/stefan436/weather_image/main/docs/icons/total cloud cover.png",
        "label": "Bewölkung zunehmend",
        "avg": {
          "WW": 3.0,
          "TTT": 2.1,
          "RR1c": 0.0,
          "Neff": 87.8
        },
        "details": [
          {
            "timestamp": "2026-01-12T14:00:00+01:00",
            "WW": "3.00",
            "TTT": 2.2,
            "RR1c": "0.00",
            "Neff": "88.00"
          },
          {
            "timestamp": "2026-01-12T15:00:00+01:00",
            "WW": "3.00",
            "TTT": 2.2,
            "RR1c": "0.00",
            "Neff": "88.00"
          },
          {
            "timestamp": "2026-01-12T16:00:00+01:00",
            "WW": "3.00",
            "TTT": 2.0,
            "RR1c": "0.00",
            "Neff": "87.00"
          },
          {
            "timestamp": "2026-01-12T17:00:00+01:00",
            "WW": "3.00",
            "TTT": 2.0,
            "RR1c": "0.00",
            "Neff": "88.00"
          }
        ]
      },
      {
        "period": "Abend",
        "icon": "https://raw.githubusercontent.com/stefan436/weather_image/main/docs/icons/light sleet.png",
        "label": "Leichter Schneeregen",
        "avg": {
          "WW": 35.5,
          "TTT": 2.0,
          "RR1c": 0.0,
          "Neff": 88.5
        },
        "details": [
          {
            "timestamp": "2026-01-12T18:00:00+01:00",
            "WW": "3.00",
            "TTT": 2.0,
            "RR1c": "0.00",
            "Neff": "88.00"
          },
          {
            "timestamp": "2026-01-12T19:00:00+01:00",
            "WW": "3.00",
            "TTT": 2.0,
            "RR1c": "0.00",
            "Neff": "88.00"
          },
          {
            "timestamp": "2026-01-12T20:00:00+01:00",
            "WW": "68.00",
            "TTT": 2.0,
            "RR1c": "0.00",
            "Neff": "89.00"
          },
          {
            "timestamp": "2026-01-12T21:00:00+01:00",
            "WW": "68.00",
            "TTT": 1.9,
            "RR1c": "0.00",
            "Neff": "89.00"
          }
        ]
      },
      {
        "period": "Spät Abends",
        "icon": "https://raw.githubusercontent.com/stefan436/weather_image/main/docs/icons/light sleet.png",
        "label": "Leichter Schneeregen",
        "avg": {
          "WW": 68.0,
          "TTT": 1.7,
          "RR1c": 0.0,
          "Neff": 90.0
        },
        "details": [
          {
            "timestamp": "2026-01-12T22:00:00+01:00",
            "WW": "68.00",
            "TTT": 1.7,
            "RR1c": "0.00",
            "Neff": "90.00"
          },
          {
            "timestamp": "2026-01-12T23:00:00+01:00",
            "WW": "68.00",
            "TTT": 1.8,
            "RR1c": "0.00",
            "Neff": "90.00"
          },
          {
            "timestamp": "2026-01-13T00:00:00+01:00",
            "WW": "68.00",
            "TTT": 1.6,
            "RR1c": "0.00",
            "Neff": "90.00"
          },
          {
            "timestamp": "2026-01-13T01:00:00+01:00",
            "WW": "68.00",
            "TTT": 1.6,
            "RR1c": "0.00",
            "Neff": "90.00"
          }
        ]
      }
    ],
    "Tue, 13.01.": [
      {
        "period": "Nacht",
        "icon": "https://raw.githubusercontent.com/stefan436/weather_image/main/docs/icons/light sleet.png",
        "label": "Leichter Schneeregen",
        "avg": {
          "WW": 68.0,
          "TTT": 1.8,
          "RR1c": 0.0,
          "Neff": 91.5
        },
        "details": [
          {
            "timestamp": "2026-01-13T02:00:00+01:00",
            "WW": "68.00",
            "TTT": 1.6,
            "RR1c": "0.00",
            "Neff": "91.00"
          },
          {
            "timestamp": "2026-01-13T03:00:00+01:00",
            "WW": "68.00",
            "TTT": 1.7,
            "RR1c": "0.00",
            "Neff": "92.00"
          },
          {
            "timestamp": "2026-01-13T04:00:00+01:00",
            "WW": "68.00",
            "TTT": 1.7,
            "RR1c": "0.00",
            "Neff": "91.00"
          },
          {
            "timestamp": "2026-01-13T05:00:00+01:00",
            "WW": "68.00",
            "TTT": 1.8,
            "RR1c": "0.00",
            "Neff": "92.00"
          }
        ]
      },
      {
        "period": "Früh",
        "icon": "https://raw.githubusercontent.com/stefan436/weather_image/main/docs/icons/light rain.png",
        "label": "Leichter Regen",
        "avg": {
          "WW": 17.5,
          "TTT": 1.7,
          "RR1c": 0.0,
          "Neff": 92.0
        },
        "details": [
          {
            "timestamp": "2026-01-13T06:00:00+01:00",
            "WW": "61.00",
            "TTT": 1.6,
            "RR1c": "0.00",
            "Neff": "92.00"
          },
          {
            "timestamp": "2026-01-13T07:00:00+01:00",
            "WW": "3.00",
            "TTT": 1.6,
            "RR1c": "0.00",
            "Neff": "92.00"
          },
          {
            "timestamp": "2026-01-13T08:00:00+01:00",
            "WW": "3.00",
            "TTT": 1.6,
            "RR1c": "0.00",
            "Neff": "92.00"
          },
          {
            "timestamp": "2026-01-13T09:00:00+01:00",
            "WW": "3.00",
            "TTT": 1.7,
            "RR1c": "0.00",
            "Neff": "92.00"
          }
        ]
      },
      {
        "period": "Mittag",
        "icon": "https://raw.githubusercontent.com/stefan436/weather_image/main/docs/icons/total cloud cover.png",
        "label": "Bewölkung zunehmend",
        "avg": {
          "WW": 2.5,
          "TTT": 2.5,
          "RR1c": 0.0,
          "Neff": 89.2
        },
        "details": [
          {
            "timestamp": "2026-01-13T10:00:00+01:00",
            "WW": "3.00",
            "TTT": 1.9,
            "RR1c": "0.00",
            "Neff": "91.00"
          },
          {
            "timestamp": "2026-01-13T11:00:00+01:00",
            "WW": "3.00",
            "TTT": 2.3,
            "RR1c": "0.00",
            "Neff": "90.00"
          },
          {
            "timestamp": "2026-01-13T12:00:00+01:00",
            "WW": "2.00",
            "TTT": 2.7,
            "RR1c": "0.00",
            "Neff": "89.00"
          },
          {
            "timestamp": "2026-01-13T13:00:00+01:00",
            "WW": "2.00",
            "TTT": 3.0,
            "RR1c": "0.00",
            "Neff": "87.00"
          }
        ]
      },
      {
        "period": "Nachmittag",
        "icon": "https://raw.githubusercontent.com/stefan436/weather_image/main/docs/icons/total cloud cover.png",
        "label": "Bewölkung zunehmend",
        "avg": {
          "WW": 3.0,
          "TTT": 3.2,
          "RR1c": 0.0,
          "Neff": 86.2
        },
        "details": [
          {
            "timestamp": "2026-01-13T14:00:00+01:00",
            "WW": "3.00",
            "TTT": 3.3,
            "RR1c": "0.00",
            "Neff": "87.00"
          },
          {
            "timestamp": "2026-01-13T15:00:00+01:00",
            "WW": "3.00",
            "TTT": 3.3,
            "RR1c": "0.00",
            "Neff": "86.00"
          },
          {
            "timestamp": "2026-01-13T16:00:00+01:00",
            "WW": "3.00",
            "TTT": 3.3,
            "RR1c": "0.00",
            "Neff": "86.00"
          },
          {
            "timestamp": "2026-01-13T17:00:00+01:00",
            "WW": "3.00",
            "TTT": 2.7,
            "RR1c": "0.00",
            "Neff": "86.00"
          }
        ]
      },
      {
        "period": "Abend",
        "icon": "https://raw.githubusercontent.com/stefan436/weather_image/main/docs/icons/light rain.png",
        "label": "Leichter Regen",
        "avg": {
          "WW": 32.0,
          "TTT": 2.0,
          "RR1c": 0.0,
          "Neff": 86.8
        },
        "details": [
          {
            "timestamp": "2026-01-13T18:00:00+01:00",
            "WW": "3.00",
            "TTT": 2.3,
            "RR1c": "0.00",
            "Neff": "86.00"
          },
          {
            "timestamp": "2026-01-13T19:00:00+01:00",
            "WW": "3.00",
            "TTT": 1.9,
            "RR1c": "0.00",
            "Neff": "87.00"
          },
          {
            "timestamp": "2026-01-13T20:00:00+01:00",
            "WW": "61.00",
            "TTT": 1.9,
            "RR1c": "0.00",
            "Neff": "87.00"
          },
          {
            "timestamp": "2026-01-13T21:00:00+01:00",
            "WW": "61.00",
            "TTT": 1.8,
            "RR1c": "0.00",
            "Neff": "87.00"
          }
        ]
      },
      {
        "period": "Spät Abends",
        "icon": "https://raw.githubusercontent.com/stefan436/weather_image/main/docs/icons/light rain.png",
        "label": "Leichter Regen",
        "avg": {
          "WW": 17.5,
          "TTT": 1.2,
          "RR1c": 0.0,
          "Neff": 87.5
        },
        "details": [
          {
            "timestamp": "2026-01-13T22:00:00+01:00",
            "WW": "61.00",
            "TTT": 1.6,
            "RR1c": "0.00",
            "Neff": "87.00"
          },
          {
            "timestamp": "2026-01-13T23:00:00+01:00",
            "WW": "3.00",
            "TTT": 1.3,
            "RR1c": "0.00",
            "Neff": "88.00"
          },
          {
            "timestamp": "2026-01-14T00:00:00+01:00",
            "WW": "3.00",
            "TTT": 1.2,
            "RR1c": "0.00",
            "Neff": "88.00"
          },
          {
            "timestamp": "2026-01-14T01:00:00+01:00",
            "WW": "3.00",
            "TTT": 1.0,
            "RR1c": "0.00",
            "Neff": "87.00"
          }
        ]
      }
    ],
    "Wed, 14.01.": [
      {
        "period": "Nacht",
        "icon": "https://raw.githubusercontent.com/stefan436/weather_image/main/docs/icons/total cloud cover.png",
        "label": "Bewölkung zunehmend",
        "avg": {
          "WW": 3.0,
          "TTT": 0.8,
          "RR1c": 0.0,
          "Neff": 86.0
        },
        "details": [
          {
            "timestamp": "2026-01-14T02:00:00+01:00",
            "WW": "3.00",
            "TTT": 0.8,
            "RR1c": "0.00",
            "Neff": "86.00"
          },
          {
            "timestamp": "2026-01-14T03:00:00+01:00",
            "WW": "3.00",
            "TTT": 0.8,
            "RR1c": "0.00",
            "Neff": "86.00"
          },
          {
            "timestamp": "2026-01-14T04:00:00+01:00",
            "WW": "3.00",
            "TTT": 0.7,
            "RR1c": "0.00",
            "Neff": "86.00"
          },
          {
            "timestamp": "2026-01-14T05:00:00+01:00",
            "WW": "3.00",
            "TTT": 0.6,
            "RR1c": "0.00",
            "Neff": "86.00"
          }
        ]
      },
      {
        "period": "Früh",
        "icon": "https://raw.githubusercontent.com/stefan436/weather_image/main/docs/icons/total cloud cover.png",
        "label": "Bewölkung zunehmend",
        "avg": {
          "WW": 3.0,
          "TTT": 0.7,
          "RR1c": 0.0,
          "Neff": 83.2
        },
        "details": [
          {
            "timestamp": "2026-01-14T06:00:00+01:00",
            "WW": "3.00",
            "TTT": 0.6,
            "RR1c": "0.00",
            "Neff": "83.00"
          },
          {
            "timestamp": "2026-01-14T07:00:00+01:00",
            "WW": "3.00",
            "TTT": 0.6,
            "RR1c": "0.00",
            "Neff": "81.00"
          },
          {
            "timestamp": "2026-01-14T08:00:00+01:00",
            "WW": "3.00",
            "TTT": 0.6,
            "RR1c": "0.00",
            "Neff": "84.00"
          },
          {
            "timestamp": "2026-01-14T09:00:00+01:00",
            "WW": "3.00",
            "TTT": 0.8,
            "RR1c": "0.00",
            "Neff": "85.00"
          }
        ]
      },
      {
        "period": "Mittag",
        "icon": "https://raw.githubusercontent.com/stefan436/weather_image/main/docs/icons/total cloud cover.png",
        "label": "Bewölkung zunehmend",
        "avg": {
          "WW": 2.5,
          "TTT": 2.1,
          "RR1c": 0.0,
          "Neff": 83.8
        },
        "details": [
          {
            "timestamp": "2026-01-14T10:00:00+01:00",
            "WW": "3.00",
            "TTT": 1.1,
            "RR1c": "0.00",
            "Neff": "84.00"
          },
          {
            "timestamp": "2026-01-14T11:00:00+01:00",
            "WW": "3.00",
            "TTT": 1.6,
            "RR1c": "0.00",
            "Neff": "84.00"
          },
          {
            "timestamp": "2026-01-14T12:00:00+01:00",
            "WW": "2.00",
            "TTT": 2.6,
            "RR1c": "0.00",
            "Neff": "83.00"
          },
          {
            "timestamp": "2026-01-14T13:00:00+01:00",
            "WW": "2.00",
            "TTT": 3.0,
            "RR1c": "0.00",
            "Neff": "84.00"
          }
        ]
      },
      {
        "period": "Nachmittag",
        "icon": "https://raw.githubusercontent.com/stefan436/weather_image/main/docs/icons/total cloud cover.png",
        "label": "Bewölkung zunehmend",
        "avg": {
          "WW": 2.0,
          "TTT": 3.1,
          "RR1c": 0.0,
          "Neff": 83.5
        },
        "details": [
          {
            "timestamp": "2026-01-14T14:00:00+01:00",
            "WW": "2.00",
            "TTT": 3.2,
            "RR1c": "0.00",
            "Neff": "84.00"
          },
          {
            "timestamp": "2026-01-14T15:00:00+01:00",
            "WW": "2.00",
            "TTT": 3.2,
            "RR1c": "0.00",
            "Neff": "84.00"
          },
          {
            "timestamp": "2026-01-14T16:00:00+01:00",
            "WW": "2.00",
            "TTT": 3.0,
            "RR1c": "0.00",
            "Neff": "83.00"
          },
          {
            "timestamp": "2026-01-14T17:00:00+01:00",
            "WW": "2.00",
            "TTT": 2.7,
            "RR1c": "0.00",
            "Neff": "83.00"
          }
        ]
      },
      {
        "period": "Abend",
        "icon": "https://raw.githubusercontent.com/stefan436/weather_image/main/docs/icons/total cloud cover.png",
        "label": "Bewölkung zunehmend",
        "avg": {
          "WW": 2.8,
          "TTT": 1.9,
          "RR1c": 0.0,
          "Neff": 83.0
        },
        "details": [
          {
            "timestamp": "2026-01-14T18:00:00+01:00",
            "WW": "2.00",
            "TTT": 2.3,
            "RR1c": "0.00",
            "Neff": "83.00"
          },
          {
            "timestamp": "2026-01-14T19:00:00+01:00",
            "WW": "3.00",
            "TTT": 1.9,
            "RR1c": "0.00",
            "Neff": "84.00"
          },
          {
            "timestamp": "2026-01-14T20:00:00+01:00",
            "WW": "3.00",
            "TTT": 1.7,
            "RR1c": "0.00",
            "Neff": "83.00"
          },
          {
            "timestamp": "2026-01-14T21:00:00+01:00",
            "WW": "3.00",
            "TTT": 1.5,
            "RR1c": "0.00",
            "Neff": "82.00"
          }
        ]
      },
      {
        "period": "Spät Abends",
        "icon": "https://raw.githubusercontent.com/stefan436/weather_image/main/docs/icons/total cloud cover.png",
        "label": "Bewölkung zunehmend",
        "avg": {
          "WW": 3.0,
          "TTT": 1.2,
          "RR1c": 0.0,
          "Neff": 82.0
        },
        "details": [
          {
            "timestamp": "2026-01-14T22:00:00+01:00",
            "WW": "3.00",
            "TTT": 1.4,
            "RR1c": "0.00",
            "Neff": "81.00"
          },
          {
            "timestamp": "2026-01-14T23:00:00+01:00",
            "WW": "3.00",
            "TTT": 1.4,
            "RR1c": "0.00",
            "Neff": "82.00"
          },
          {
            "timestamp": "2026-01-15T00:00:00+01:00",
            "WW": "3.00",
            "TTT": 1.2,
            "RR1c": "0.00",
            "Neff": "83.00"
          },
          {
            "timestamp": "2026-01-15T01:00:00+01:00",
            "WW": "3.00",
            "TTT": 1.0,
            "RR1c": "0.00",
            "Neff": "82.00"
          }
        ]
      }
    ],
    "Thu, 15.01.": [
      {
        "period": "Nacht",
        "icon": "https://raw.githubusercontent.com/stefan436/weather_image/main/docs/icons/total cloud cover.png",
        "label": "Bewölkung zunehmend",
        "avg": {
          "WW": 3.0,
          "TTT": 0.8,
          "RR1c": 0.0,
          "Neff": 85.0
        },
        "details": [
          {
            "timestamp": "2026-01-15T02:00:00+01:00",
            "WW": "3.00",
            "TTT": 0.9,
            "RR1c": "0.00",
            "Neff": "85.00"
          },
          {
            "timestamp": "2026-01-15T03:00:00+01:00",
            "WW": "3.00",
            "TTT": 0.8,
            "RR1c": "0.00",
            "Neff": "85.00"
          },
          {
            "timestamp": "2026-01-15T04:00:00+01:00",
            "WW": "3.00",
            "TTT": 0.7,
            "RR1c": "0.00",
            "Neff": "85.00"
          },
          {
            "timestamp": "2026-01-15T05:00:00+01:00",
            "WW": "3.00",
            "TTT": 0.7,
            "RR1c": "0.00",
            "Neff": "85.00"
          }
        ]
      },
      {
        "period": "Früh",
        "icon": "https://raw.githubusercontent.com/stefan436/weather_image/main/docs/icons/total cloud cover.png",
        "label": "Bewölkung zunehmend",
        "avg": {
          "WW": 3.0,
          "TTT": 0.9,
          "RR1c": 0.0,
          "Neff": 86.8
        },
        "details": [
          {
            "timestamp": "2026-01-15T06:00:00+01:00",
            "WW": "3.00",
            "TTT": 0.8,
            "RR1c": "0.00",
            "Neff": "86.00"
          },
          {
            "timestamp": "2026-01-15T07:00:00+01:00",
            "WW": "3.00",
            "TTT": 0.8,
            "RR1c": "0.00",
            "Neff": "87.00"
          },
          {
            "timestamp": "2026-01-15T08:00:00+01:00",
            "WW": "3.00",
            "TTT": 0.8,
            "RR1c": "0.00",
            "Neff": "87.00"
          },
          {
            "timestamp": "2026-01-15T09:00:00+01:00",
            "WW": "3.00",
            "TTT": 1.1,
            "RR1c": "0.00",
            "Neff": "87.00"
          }
        ]
      },
      {
        "period": "Mittag",
        "icon": "https://raw.githubusercontent.com/stefan436/weather_image/main/docs/icons/total cloud cover.png",
        "label": "Bewölkung zunehmend",
        "avg": {
          "WW": 2.0,
          "TTT": 2.2,
          "RR1c": 0.0,
          "Neff": 85.3
        },
        "details": [
          {
            "timestamp": "2026-01-15T10:00:00+01:00",
            "WW": "2.00",
            "TTT": 1.4,
            "RR1c": "0.00",
            "Neff": "87.00"
          },
          {
            "timestamp": "2026-01-15T11:00:00+01:00",
            "WW": "2.00",
            "TTT": 2.0,
            "RR1c": "0.00",
            "Neff": "86.00"
          },
          {
            "timestamp": "2026-01-15T12:00:00+01:00",
            "WW": "2.00",
            "TTT": 3.4,
            "RR1c": "0.00",
            "Neff": "83.00"
          }
        ]
      }
    ]
  },
  "timeSteps": [
    "2026-01-05T12:00:00+00:00",
    "2026-01-05T13:00:00+00:00",
    "2026-01-05T14:00:00+00:00",
    "2026-01-05T15:00:00+00:00",
    "2026-01-05T16:00:00+00:00",
    "2026-01-05T17:00:00+00:00",
    "2026-01-05T18:00:00+00:00",
    "2026-01-05T19:00:00+00:00",
    "2026-01-05T20:00:00+00:00",
    "2026-01-05T21:00:00+00:00",
    "2026-01-05T22:00:00+00:00",
    "2026-01-05T23:00:00+00:00",
    "2026-01-06T00:00:00+00:00",
    "2026-01-06T01:00:00+00:00",
    "2026-01-06T02:00:00+00:00",
    "2026-01-06T03:00:00+00:00",
    "2026-01-06T04:00:00+00:00",
    "2026-01-06T05:00:00+00:00",
    "2026-01-06T06:00:00+00:00",
    "2026-01-06T07:00:00+00:00",
    "2026-01-06T08:00:00+00:00",
    "2026-01-06T09:00:00+00:00",
    "2026-01-06T10:00:00+00:00",
    "2026-01-06T11:00:00+00:00",
    "2026-01-06T12:00:00+00:00",
    "2026-01-06T13:00:00+00:00",
    "2026-01-06T14:00:00+00:00",
    "2026-01-06T15:00:00+00:00",
    "2026-01-06T16:00:00+00:00",
    "2026-01-06T17:00:00+00:00",
    "2026-01-06T18:00:00+00:00",
    "2026-01-06T19:00:00+00:00",
    "2026-01-06T20:00:00+00:00",
    "2026-01-06T21:00:00+00:00",
    "2026-01-06T22:00:00+00:00",
    "2026-01-06T23:00:00+00:00",
    "2026-01-07T00:00:00+00:00",
    "2026-01-07T01:00:00+00:00",
    "2026-01-07T02:00:00+00:00",
    "2026-01-07T03:00:00+00:00",
    "2026-01-07T04:00:00+00:00",
    "2026-01-07T05:00:00+00:00",
    "2026-01-07T06:00:00+00:00",
    "2026-01-07T07:00:00+00:00",
    "2026-01-07T08:00:00+00:00",
    "2026-01-07T09:00:00+00:00",
    "2026-01-07T10:00:00+00:00",
    "2026-01-07T11:00:00+00:00",
    "2026-01-07T12:00:00+00:00",
    "2026-01-07T13:00:00+00:00",
    "2026-01-07T14:00:00+00:00",
    "2026-01-07T15:00:00+00:00",
    "2026-01-07T16:00:00+00:00",
    "2026-01-07T17:00:00+00:00",
    "2026-01-07T18:00:00+00:00",
    "2026-01-07T19:00:00+00:00",
    "2026-01-07T20:00:00+00:00",
    "2026-01-07T21:00:00+00:00",
    "2026-01-07T22:00:00+00:00",
    "2026-01-07T23:00:00+00:00",
    "2026-01-08T00:00:00+00:00",
    "2026-01-08T01:00:00+00:00",
    "2026-01-08T02:00:00+00:00",
    "2026-01-08T03:00:00+00:00",
    "2026-01-08T04:00:00+00:00",
    "2026-01-08T05:00:00+00:00",
    "2026-01-08T06:00:00+00:00",
    "2026-01-08T07:00:00+00:00",
    "2026-01-08T08:00:00+00:00",
    "2026-01-08T09:00:00+00:00",
    "2026-01-08T10:00:00+00:00",
    "2026-01-08T11:00:00+00:00",
    "2026-01-08T12:00:00+00:00",
    "2026-01-08T13:00:00+00:00",
    "2026-01-08T14:00:00+00:00",
    "2026-01-08T15:00:00+00:00",
    "2026-01-08T16:00:00+00:00",
    "2026-01-08T17:00:00+00:00",
    "2026-01-08T18:00:00+00:00",
    "2026-01-08T19:00:00+00:00",
    "2026-01-08T20:00:00+00:00",
    "2026-01-08T21:00:00+00:00",
    "2026-01-08T22:00:00+00:00",
    "2026-01-08T23:00:00+00:00",
    "2026-01-09T00:00:00+00:00",
    "2026-01-09T01:00:00+00:00",
    "2026-01-09T02:00:00+00:00",
    "2026-01-09T03:00:00+00:00",
    "2026-01-09T04:00:00+00:00",
    "2026-01-09T05:00:00+00:00",
    "2026-01-09T06:00:00+00:00",
    "2026-01-09T07:00:00+00:00",
    "2026-01-09T08:00:00+00:00",
    "2026-01-09T09:00:00+00:00",
    "2026-01-09T10:00:00+00:00",
    "2026-01-09T11:00:00+00:00",
    "2026-01-09T12:00:00+00:00",
    "2026-01-09T13:00:00+00:00",
    "2026-01-09T14:00:00+00:00",
    "2026-01-09T15:00:00+00:00",
    "2026-01-09T16:00:00+00:00",
    "2026-01-09T17:00:00+00:00",
    "2026-01-09T18:00:00+00:00",
    "2026-01-09T19:00:00+00:00",
    "2026-01-09T20:00:00+00:00",
    "2026-01-09T21:00:00+00:00",
    "2026-01-09T22:00:00+00:00",
    "2026-01-09T23:00:00+00:00",
    "2026-01-10T00:00:00+00:00",
    "2026-01-10T01:00:00+00:00",
    "2026-01-10T02:00:00+00:00",
    "2026-01-10T03:00:00+00:00",
    "2026-01-10T04:00:00+00:00",
    "2026-01-10T05:00:00+00:00",
    "2026-01-10T06:00:00+00:00",
    "2026-01-10T07:00:00+00:00",
    "2026-01-10T08:00:00+00:00",
    "2026-01-10T09:00:00+00:00",
    "2026-01-10T10:00:00+00:00",
    "2026-01-10T11:00:00+00:00",
    "2026-01-10T12:00:00+00:00",
    "2026-01-10T13:00:00+00:00",
    "2026-01-10T14:00:00+00:00",
    "2026-01-10T15:00:00+00:00",
    "2026-01-10T16:00:00+00:00",
    "2026-01-10T17:00:00+00:00",
    "2026-01-10T18:00:00+00:00",
    "2026-01-10T19:00:00+00:00",
    "2026-01-10T20:00:00+00:00",
    "2026-01-10T21:00:00+00:00",
    "2026-01-10T22:00:00+00:00",
    "2026-01-10T23:00:00+00:00",
    "2026-01-11T00:00:00+00:00",
    "2026-01-11T01:00:00+00:00",
    "2026-01-11T02:00:00+00:00",
    "2026-01-11T03:00:00+00:00",
    "2026-01-11T04:00:00+00:00",
    "2026-01-11T05:00:00+00:00",
    "2026-01-11T06:00:00+00:00",
    "2026-01-11T07:00:00+00:00",
    "2026-01-11T08:00:00+00:00",
    "2026-01-11T09:00:00+00:00",
    "2026-01-11T10:00:00+00:00",
    "2026-01-11T11:00:00+00:00",
    "2026-01-11T12:00:00+00:00",
    "2026-01-11T13:00:00+00:00",
    "2026-01-11T14:00:00+00:00",
    "2026-01-11T15:00:00+00:00",
    "2026-01-11T16:00:00+00:00",
    "2026-01-11T17:00:00+00:00",
    "2026-01-11T18:00:00+00:00",
    "2026-01-11T19:00:00+00:00",
    "2026-01-11T20:00:00+00:00",
    "2026-01-11T21:00:00+00:00",
    "2026-01-11T22:00:00+00:00",
    "2026-01-11T23:00:00+00:00",
    "2026-01-12T00:00:00+00:00",
    "2026-01-12T01:00:00+00:00",
    "2026-01-12T02:00:00+00:00",
    "2026-01-12T03:00:00+00:00",
    "2026-01-12T04:00:00+00:00",
    "2026-01-12T05:00:00+00:00",
    "2026-01-12T06:00:00+00:00",
    "2026-01-12T07:00:00+00:00",
    "2026-01-12T08:00:00+00:00",
    "2026-01-12T09:00:00+00:00",
    "2026-01-12T10:00:00+00:00",
    "2026-01-12T11:00:00+00:00",
    "2026-01-12T12:00:00+00:00",
    "2026-01-12T13:00:00+00:00",
    "2026-01-12T14:00:00+00:00",
    "2026-01-12T15:00:00+00:00",
    "2026-01-12T16:00:00+00:00",
    "2026-01-12T17:00:00+00:00",
    "2026-01-12T18:00:00+00:00",
    "2026-01-12T19:00:00+00:00",
    "2026-01-12T20:00:00+00:00",
    "2026-01-12T21:00:00+00:00",
    "2026-01-12T22:00:00+00:00",
    "2026-01-12T23:00:00+00:00",
    "2026-01-13T00:00:00+00:00",
    "2026-01-13T01:00:00+00:00",
    "2026-01-13T02:00:00+00:00",
    "2026-01-13T03:00:00+00:00",
    "2026-01-13T04:00:00+00:00",
    "2026-01-13T05:00:00+00:00",
    "2026-01-13T06:00:00+00:00",
    "2026-01-13T07:00:00+00:00",
    "2026-01-13T08:00:00+00:00",
    "2026-01-13T09:00:00+00:00",
    "2026-01-13T10:00:00+00:00",
    "2026-01-13T11:00:00+00:00",
    "2026-01-13T12:00:00+00:00",
    "2026-01-13T13:00:00+00:00",
    "2026-01-13T14:00:00+00:00",
    "2026-01-13T15:00:00+00:00",
    "2026-01-13T16:00:00+00:00",
    "2026-01-13T17:00:00+00:00",
    "2026-01-13T18:00:00+00:00",
    "2026-01-13T19:00:00+00:00",
    "2026-01-13T20:00:00+00:00",
    "2026-01-13T21:00:00+00:00",
    "2026-01-13T22:00:00+00:00",
    "2026-01-13T23:00:00+00:00",
    "2026-01-14T00:00:00+00:00",
    "2026-01-14T01:00:00+00:00",
    "2026-01-14T02:00:00+00:00",
    "2026-01-14T03:00:00+00:00",
    "2026-01-14T04:00:00+00:00",
    "2026-01-14T05:00:00+00:00",
    "2026-01-14T06:00:00+00:00",
    "2026-01-14T07:00:00+00:00",
    "2026-01-14T08:00:00+00:00",
    "2026-01-14T09:00:00+00:00",
    "2026-01-14T10:00:00+00:00",
    "2026-01-14T11:00:00+00:00",
    "2026-01-14T12:00:00+00:00",
    "2026-01-14T13:00:00+00:00",
    "2026-01-14T14:00:00+00:00",
    "2026-01-14T15:00:00+00:00",
    "2026-01-14T16:00:00+00:00",
    "2026-01-14T17:00:00+00:00",
    "2026-01-14T18:00:00+00:00",
    "2026-01-14T19:00:00+00:00",
    "2026-01-14T20:00:00+00:00",
    "2026-01-14T21:00:00+00:00",
    "2026-01-14T22:00:00+00:00",
    "2026-01-14T23:00:00+00:00",
    "2026-01-15T00:00:00+00:00",
    "2026-01-15T01:00:00+00:00",
    "2026-01-15T02:00:00+00:00",
    "2026-01-15T03:00:00+00:00",
    "2026-01-15T04:00:00+00:00",
    "2026-01-15T05:00:00+00:00",
    "2026-01-15T06:00:00+00:00",
    "2026-01-15T07:00:00+00:00",
    "2026-01-15T08:00:00+00:00",
    "2026-01-15T09:00:00+00:00",
    "2026-01-15T10:00:00+00:00",
    "2026-01-15T11:00:00+00:00"
  ],
  "parameters": {
    "WW": [
      "1.00",
      "1.00",
      "1.00",
      "1.00",
      "1.00",
      "1.00",
      "1.00",
      "1.00",
      "1.00",
      "1.00",
      "1.00",
      "1.00",
      "1.00",
      "1.00",
      "1.00",
      "1.00",
      "1.00",
      "2.00",
      "2.00",
      "3.00",
      "3.00",
      "3.00",
      "3.00",
      "2.00",
      "2.00",
      "2.00",
      "2.00",
      "2.00",
      "2.00",
      "3.00",
      "3.00",
      "3.00",
      "3.00",
      "3.00",
      "3.00",
      "3.00",
      "3.00",
      "3.00",
      "3.00",
      "2.00",
      "2.00",
      "2.00",
      "2.00",
      "2.00",
      "2.00",
      "2.00",
      "2.00",
      "1.00",
      "1.00",
      "1.00",
      "1.00",
      "1.00",
      "1.00",
      "1.00",
      "1.00",
      "2.00",
      "2.00",
      "2.00",
      "2.00",
      "3.00",
      "3.00",
      "3.00",
      "3.00",
      "3.00",
      "3.00",
      "3.00",
      "3.00",
      "3.00",
      "3.00",
      "3.00",
      "3.00",
      "3.00",
      "3.00",
      "3.00",
      "3.00",
      "71.00",
      "71.00",
      "71.00",
      "71.00",
      "71.00",
      "71.00",
      "68.00",
      "68.00",
      "68.00",
      "61.00",
      "61.00",
      "61.00",
      "61.00",
      "61.00",
      "61.00",
      "61.00",
      "61.00",
      "61.00",
      "61.00",
      "3.00",
      "3.00",
      "3.00",
      "3.00",
      "3.00",
      "3.00",
      "3.00",
      "61.00",
      "68.00",
      "68.00",
      "61.00",
      "68.00",
      "68.00",
      "68.00",
      "68.00",
      "68.00",
      "68.00",
      "71.00",
      "71.00",
      "71.00",
      "71.00",
      "71.00",
      "71.00",
      "71.00",
      "71.00",
      "71.00",
      "71.00",
      "71.00",
      "71.00",
      "71.00",
      "71.00",
      "71.00",
      "71.00",
      "71.00",
      "71.00",
      "71.00",
      "71.00",
      "71.00",
      "71.00",
      "71.00",
      "71.00",
      "71.00",
      "71.00",
      "71.00",
      "71.00",
      "71.00",
      "71.00",
      "3.00",
      "3.00",
      "3.00",
      "3.00",
      "3.00",
      "3.00",
      "3.00",
      "3.00",
      "3.00",
      "3.00",
      "3.00",
      "3.00",
      "68.00",
      "3.00",
      "3.00",
      "3.00",
      "3.00",
      "3.00",
      "3.00",
      "3.00",
      "3.00",
      "3.00",
      "3.00",
      "3.00",
      "3.00",
      "3.00",
      "3.00",
      "3.00",
      "3.00",
      "3.00",
      "3.00",
      "3.00",
      "3.00",
      "3.00",
      "68.00",
      "68.00",
      "68.00",
      "68.00",
      "68.00",
      "68.00",
      "68.00",
      "68.00",
      "68.00",
      "68.00",
      "61.00",
      "3.00",
      "3.00",
      "3.00",
      "3.00",
      "3.00",
      "2.00",
      "2.00",
      "3.00",
      "3.00",
      "3.00",
      "3.00",
      "3.00",
      "3.00",
      "61.00",
      "61.00",
      "61.00",
      "3.00",
      "3.00",
      "3.00",
      "3.00",
      "3.00",
      "3.00",
      "3.00",
      "3.00",
      "3.00",
      "3.00",
      "3.00",
      "3.00",
      "3.00",
      "2.00",
      "2.00",
      "2.00",
      "2.00",
      "2.00",
      "2.00",
      "2.00",
      "3.00",
      "3.00",
      "3.00",
      "3.00",
      "3.00",
      "3.00",
      "3.00",
      "3.00",
      "3.00",
      "3.00",
      "3.00",
      "3.00",
      "3.00",
      "3.00",
      "3.00",
      "2.00",
      "2.00",
      "2.00"
    ],
    "TTT": [
      "267.85",
      "268.35",
      "268.35",
      "268.15",
      "267.65",
      "266.85",
      "266.05",
      "265.45",
      "264.85",
      "264.25",
      "263.85",
      "263.65",
      "263.15",
      "263.05",
      "262.95",
      "262.95",
      "262.65",
      "262.55",
      "262.65",
      "262.95",
      "263.55",
      "264.55",
      "265.55",
      "266.55",
      "267.45",
      "268.05",
      "268.15",
      "268.15",
      "268.15",
      "267.75",
      "267.35",
      "267.15",
      "266.65",
      "266.25",
      "266.05",
      "265.65",
      "265.25",
      "265.05",
      "264.85",
      "264.25",
      "264.15",
      "264.15",
      "263.65",
      "263.75",
      "264.05",
      "264.85",
      "265.65",
      "266.75",
      "267.65",
      "268.35",
      "268.65",
      "268.45",
      "267.85",
      "267.15",
      "266.75",
      "266.45",
      "266.45",
      "266.85",
      "267.15",
      "267.35",
      "267.95",
      "268.25",
      "268.65",
      "268.95",
      "269.15",
      "269.45",
      "269.65",
      "269.95",
      "270.35",
      "270.95",
      "271.45",
      "272.05",
      "272.65",
      "273.35",
      "273.55",
      "273.35",
      "273.35",
      "273.25",
      "273.35",
      "273.75",
      "273.95",
      "274.35",
      "274.65",
      "274.85",
      "275.05",
      "275.55",
      "275.65",
      "275.85",
      "275.85",
      "276.15",
      "276.35",
      "276.55",
      "276.55",
      "276.75",
      "277.35",
      "277.65",
      "277.45",
      "277.75",
      "277.65",
      "277.25",
      "276.85",
      "276.55",
      "276.25",
      "275.95",
      "275.85",
      "275.95",
      "275.75",
      "275.65",
      "275.55",
      "275.55",
      "275.45",
      "275.25",
      "275.25",
      "275.15",
      "275.05",
      "275.15",
      "274.95",
      "275.05",
      "275.35",
      "275.35",
      "275.05",
      "275.05",
      "274.85",
      "274.25",
      "273.95",
      "273.45",
      "273.05",
      "273.05",
      "272.95",
      "272.85",
      "272.75",
      "272.55",
      "272.35",
      "272.25",
      "272.15",
      "272.05",
      "271.95",
      "271.85",
      "271.85",
      "271.75",
      "272.35",
      "272.75",
      "273.25",
      "273.75",
      "274.05",
      "273.95",
      "274.05",
      "273.75",
      "273.35",
      "272.85",
      "272.75",
      "272.65",
      "272.65",
      "272.45",
      "272.45",
      "272.45",
      "272.25",
      "272.25",
      "272.35",
      "272.45",
      "272.45",
      "272.55",
      "272.95",
      "273.15",
      "273.25",
      "273.75",
      "274.15",
      "274.55",
      "275.05",
      "275.35",
      "275.35",
      "275.15",
      "275.15",
      "275.15",
      "275.15",
      "275.15",
      "275.05",
      "274.85",
      "274.95",
      "274.75",
      "274.75",
      "274.75",
      "274.85",
      "274.85",
      "274.95",
      "274.75",
      "274.75",
      "274.75",
      "274.85",
      "275.05",
      "275.45",
      "275.85",
      "276.15",
      "276.45",
      "276.45",
      "276.45",
      "275.85",
      "275.45",
      "275.05",
      "275.05",
      "274.95",
      "274.75",
      "274.45",
      "274.35",
      "274.15",
      "273.95",
      "273.95",
      "273.85",
      "273.75",
      "273.75",
      "273.75",
      "273.75",
      "273.95",
      "274.25",
      "274.75",
      "275.75",
      "276.15",
      "276.35",
      "276.35",
      "276.15",
      "275.85",
      "275.45",
      "275.05",
      "274.85",
      "274.65",
      "274.55",
      "274.55",
      "274.35",
      "274.15",
      "274.05",
      "273.95",
      "273.85",
      "273.85",
      "273.95",
      "273.95",
      "273.95",
      "274.25",
      "274.55",
      "275.15",
      "276.55"
    ],
    "RR1c": [
      "0.00",
      "0.00",
      "0.00",
      "0.00",
      "0.00",
      "0.00",
      "0.00",
      "0.00",
      "0.00",
      "0.00",
      "0.00",
      "0.00",
      "0.00",
      "0.00",
      "0.00",
      "0.00",
      "0.00",
      "0.00",
      "0.00",
      "0.00",
      "0.00",
      "0.00",
      "0.00",
      "0.00",
      "0.00",
      "0.00",
      "0.00",
      "0.00",
      "0.00",
      "0.00",
      "0.00",
      "0.00",
      "0.00",
      "0.00",
      "0.00",
      "0.00",
      "0.00",
      "0.00",
      "0.00",
      "0.00",
      "0.00",
      "0.00",
      "0.00",
      "0.00",
      "0.00",
      "0.00",
      "0.00",
      "0.00",
      "0.00",
      "0.00",
      "0.00",
      "0.00",
      "0.00",
      "0.00",
      "0.00",
      "0.00",
      "0.00",
      "0.00",
      "0.00",
      "0.00",
      "0.00",
      "0.00",
      "0.00",
      "0.00",
      "0.00",
      "0.00",
      "0.00",
      "0.00",
      "0.00",
      "0.00",
      "0.00",
      "0.00",
      "0.00",
      "0.00",
      "0.00",
      "0.30",
      "0.10",
      "0.10",
      "0.20",
      "0.20",
      "0.30",
      "0.40",
      "0.40",
      "0.40",
      "0.40",
      "0.40",
      "0.30",
      "0.30",
      "0.30",
      "0.30",
      "0.30",
      "0.30",
      "0.40",
      "0.40",
      "0.00",
      "0.00",
      "0.00",
      "0.00",
      "0.00",
      "0.00",
      "0.00",
      "0.00",
      "0.00",
      "0.00",
      "0.00",
      "0.00",
      "0.00",
      "0.00",
      "0.00",
      "0.00",
      "0.00",
      "0.00",
      "0.80",
      "0.80",
      "0.70",
      "0.10",
      "0.20",
      "0.10",
      "0.20",
      "0.20",
      "0.10",
      "0.10",
      "0.10",
      "0.10",
      "0.10",
      "0.10",
      "0.20",
      "0.10",
      "0.10",
      "0.10",
      "0.10",
      "0.10",
      "0.10",
      "0.10",
      "0.10",
      "0.10",
      "0.10",
      "0.10",
      "0.10",
      "0.30",
      "0.40",
      "0.00",
      "0.00",
      "0.00",
      "0.00",
      "0.00",
      "0.00",
      "0.00",
      "0.00",
      "0.00",
      "0.00",
      "0.00",
      "0.00",
      "0.00",
      "0.00",
      "0.00",
      "0.00",
      "0.00",
      "0.00",
      "0.00",
      "0.00",
      "0.00",
      "0.00",
      "0.00",
      "0.00",
      "0.00",
      "0.00",
      "0.00",
      "0.00",
      "0.00",
      "0.00",
      "0.00",
      "0.00",
      "0.00",
      "0.00",
      "0.00",
      "0.00",
      "0.00",
      "0.00",
      "0.00",
      "0.00",
      "0.00",
      "0.00",
      "0.00",
      "0.00",
      "0.00",
      "0.00",
      "0.00",
      "0.00",
      "0.00",
      "0.00",
      "0.00",
      "0.00",
      "0.00",
      "0.00",
      "0.00",
      "0.00",
      "0.00",
      "0.00",
      "0.00",
      "0.00",
      "0.00",
      "0.00",
      "0.00",
      "0.00",
      "0.00",
      "0.00",
      "0.00",
      "0.00",
      "0.00",
      "0.00",
      "0.00",
      "0.00",
      "0.00",
      "0.00",
      "0.00",
      "0.00",
      "0.00",
      "0.00",
      "0.00",
      "0.00",
      "0.00",
      "0.00",
      "0.00",
      "0.00",
      "0.00",
      "0.00",
      "0.00",
      "0.00",
      "0.00",
      "0.00",
      "0.00",
      "0.00",
      "0.00",
      "0.00",
      "0.00",
      "0.00",
      "0.00",
      "0.00",
      "0.00"
    ],
    "Neff": [
      "49.00",
      "48.00",
      "42.00",
      "40.00",
      "37.00",
      "38.00",
      "39.00",
      "38.00",
      "39.00",
      "37.00",
      "39.00",
      "41.00",
      "43.00",
      "46.00",
      "47.00",
      "54.00",
      "58.00",
      "62.00",
      "65.00",
      "68.00",
      "71.00",
      "72.00",
      "70.00",
      "69.00",
      "71.00",
      "72.00",
      "72.00",
      "75.00",
      "75.00",
      "77.00",
      "77.00",
      "77.00",
      "76.00",
      "75.00",
      "76.00",
      "75.00",
      "73.00",
      "73.00",
      "72.00",
      "71.00",
      "70.00",
      "71.00",
      "69.00",
      "71.00",
      "71.00",
      "64.00",
      "59.00",
      "53.00",
      "43.00",
      "41.00",
      "38.00",
      "43.00",
      "43.00",
      "48.00",
      "57.00",
      "58.00",
      "61.00",
      "65.00",
      "66.00",
      "70.00",
      "75.00",
      "77.00",
      "78.00",
      "77.00",
      "78.00",
      "78.00",
      "76.00",
      "77.00",
      "76.00",
      "81.00",
      "80.00",
      "82.00",
      "86.00",
      "87.00",
      "87.00",
      "88.00",
      "89.00",
      "90.00",
      "93.00",
      "93.00",
      "94.00",
      "95.00",
      "96.00",
      "96.00",
      "97.00",
      "97.00",
      "95.00",
      "95.00",
      "95.00",
      "95.00",
      "92.00",
      "91.00",
      "89.00",
      "88.00",
      "87.00",
      "84.00",
      "85.00",
      "86.00",
      "85.00",
      "84.00",
      "87.00",
      "88.00",
      "91.00",
      "93.00",
      "94.00",
      "93.00",
      "94.00",
      "95.00",
      "95.00",
      "96.00",
      "97.00",
      "96.00",
      "96.00",
      "96.00",
      "94.00",
      "93.00",
      "93.00",
      "92.00",
      "92.00",
      "91.00",
      "91.00",
      "91.00",
      "90.00",
      "92.00",
      "91.00",
      "91.00",
      "92.00",
      "92.00",
      "92.00",
      "91.00",
      "90.00",
      "89.00",
      "89.00",
      "89.00",
      "87.00",
      "84.00",
      "83.00",
      "82.00",
      "81.00",
      "82.00",
      "82.00",
      "82.00",
      "82.00",
      "82.00",
      "82.00",
      "83.00",
      "84.00",
      "84.00",
      "85.00",
      "87.00",
      "90.00",
      "89.00",
      "89.00",
      "89.00",
      "89.00",
      "89.00",
      "91.00",
      "90.00",
      "89.00",
      "90.00",
      "90.00",
      "89.00",
      "89.00",
      "89.00",
      "89.00",
      "88.00",
      "89.00",
      "88.00",
      "88.00",
      "88.00",
      "88.00",
      "87.00",
      "88.00",
      "88.00",
      "88.00",
      "89.00",
      "89.00",
      "90.00",
      "90.00",
      "90.00",
      "90.00",
      "91.00",
      "92.00",
      "91.00",
      "92.00",
      "92.00",
      "92.00",
      "92.00",
      "92.00",
      "91.00",
      "90.00",
      "89.00",
      "87.00",
      "87.00",
      "86.00",
      "86.00",
      "86.00",
      "86.00",
      "87.00",
      "87.00",
      "87.00",
      "87.00",
      "88.00",
      "88.00",
      "87.00",
      "86.00",
      "86.00",
      "86.00",
      "86.00",
      "83.00",
      "81.00",
      "84.00",
      "85.00",
      "84.00",
      "84.00",
      "83.00",
      "84.00",
      "84.00",
      "84.00",
      "83.00",
      "83.00",
      "83.00",
      "84.00",
      "83.00",
      "82.00",
      "81.00",
      "82.00",
      "83.00",
      "82.00",
      "85.00",
      "85.00",
      "85.00",
      "85.00",
      "86.00",
      "87.00",
      "87.00",
      "87.00",
      "87.00",
      "86.00",
      "83.00"
    ]
  }
}